aosp_easy/__init__.py
aosp_easy/aosp_easy.py
aosp_easy/create_app.py
aosp_easy/create_service.py
aosp_easy-0.2.0.dist-info/METADATA
aosp_easy-0.2.0.dist-info/WHEEL
aosp_easy-0.2.0.dist-info/entry_points.txt
aosp_easy-0.2.0.dist-info/top_level.txt
aosp_easy-0.2.0.dist-info/RECORD
