Metadata-Version: 2.1
Name: aosp-easy
Version: 0.2.0
Summary: make aosp easy
Home-page: https://github.com/passion-coder-min/aosp_easy
Author: min
Author-email: testmin@outlook.com
License: MIT
Platform: UNKNOWN
Classifier: Programming Language :: Python :: 3
Classifier: License :: OSI Approved :: MIT License
Classifier: Operating System :: OS Independent
Requires-Python: >=3.0
